cipher/__init__.py
cipher/cli.py
cipher/core.py
cipher/utils.py
cipherx-1.0.1.dist-info/METADATA
cipherx-1.0.1.dist-info/WHEEL
cipherx-1.0.1.dist-info/entry_points.txt
cipherx-1.0.1.dist-info/top_level.txt
cipherx-1.0.1.dist-info/RECORD
